<?xml version="1.0" encoding="utf-8" ?>
<!--
  ~ Copyright (c) 2023 NSTDA
  -->
<odoo>
    <record id="ni_encounter_diagnosis_view_form" model="ir.ui.view">
        <field name="name">ni.encounter.diagnosis.view.form</field>
        <field name="model">ni.encounter.diagnosis</field>
        <field name="arch" type="xml">
            <form string="">
                <sheet>
                    <field name="encounter_id" invisible="1" />
                    <field name="patient_id" invisible="1" />
                    <field name="company_id" invisible="1" />
                    <field name="sequence" invisible="1" />
                    <field name="role_decoration" invisible="1" />
                    <group>
                        <field name="code_id" attrs="{'readonly': [('id', '!=', False)]}" options="{'no_open': True}" />
                    </group>
                    <group>
                        <group>
                            <field
                                name="role_id"
                                widget="radio"
                                options="{'no_open': True}"
                                attrs="{'required': [('is_diagnosis', '=', True)], 'invisible': [('is_diagnosis', '=', False)]}"
                            />
                            <field name="class_id" options="{'no_open': True}" />
                            <field name="severity" widget="radio" options="{'horizontal': True}" />
                        </group>
                        <group>
                            <field name="is_diagnosis" />
                            <field name="is_problem" />
                        </group>
                    </group>
                </sheet>
            </form>
        </field>
    </record>
    <record id="ni_encounter_diagnosis_view_tree" model="ir.ui.view">
        <field name="name">ni.encounter.diagnosis.view.tree</field>
        <field name="model">ni.encounter.diagnosis</field>
        <field name="arch" type="xml">
            <tree decoration-muted="is_problem and not is_diagnosis">
                <field name="company_id" invisible="1" />
                <field name="encounter_id" invisible="1" />
                <field name="patient_id" invisible="1" />
                <field name="role_decoration" invisible="1" />
                <field name="is_diagnosis" invisible="1" />
                <field name="is_problem" invisible="1" />
                <field name="sequence" widget="handle" />
                <field name="code_id" />
                <field
                    name="severity"
                    optional="hide"
                    decoration-danger="severity == 'severe'"
                    decoration-warning="severity == 'moderate'"
                />
                <field
                    name="role_id"
                    widget="badge"
                    decoration-primary="role_decoration == 'primary'"
                    decoration-success="role_decoration == 'success'"
                    decoration-info="role_decoration == 'info'"
                    decoration-warning="role_decoration == 'warning'"
                    decoration-danger="role_decoration == 'danger'"
                    decoration-muted="role_decoration == 'muted'"
                />
                <field name="class_id" optional="show" />
                <field name="create_uid" optional="hide" />
                <field name="create_date" optional="hide" />
                <control>
                    <create string="Add Diagnosis" context="{'default_is_diagnosis': True}" />
                    <create string="Add Chronic" context="{'default_is_problem': True}" />
                </control>
            </tree>
        </field>
    </record>
    <record id="ni_encounter_diagnosis_view_kanban" model="ir.ui.view">
        <field name="name">ni.encounter.diagnosis.view.kanban</field>
        <field name="model">ni.encounter.diagnosis</field>
        <field name="arch" type="xml">
            <kanban>
                <field name="name" />
                <field name="code" />
                <field name="role_id" />
                <field name="severity" />
                <templates>
                    <t t-name="kanban-box">
                        <div t-attf-class="oe_kanban_global_click">
                            <div class="o_kanban_record_top">
                                <div class="o_kanban_record_headings">
                                    <strong class="o_kanban_record_title d">
                                        <field name="name" />
                                    </strong>
                                </div>
                                <div class="me-1 small text-body">
                                    <field name="code" />
                                </div>
                            </div>
                            <div class="o_kanban_record_bottom">
                                <div class="oe_kanban_bottom_left">
                                    <field name="role_id" />
                                </div>
                                <div class="oe_kanban_bottom_right mr4">
                                    <field
                                        name="severity"
                                        widget="label_selection"
                                        options="{'classes': {'mild': 'default', 'moderate': 'warning', 'severe':'danger'}}"
                                    />
                                </div>
                            </div>
                        </div>
                    </t>
                </templates>
            </kanban>
        </field>
    </record>
</odoo>
